{
  "date": "2026-03-15",
  "generated_at": "2026-03-15T13:30:10",
  "evening_generated_at": "2026-03-14T21:08:27",
  "mode": "morning",
  "races": [
    {
      "race_id": "202606020611",
      "race_name": "スプリングステークス",
      "grade": "G2",
      "venue": "中山",
      "distance": "芝1800m",
      "track_condition": "",
      "predicted_at": "2026-03-15T13:30:07",
      "predictions": [
        {
          "予測順位": 1,
          "馬番": 12,
          "馬名": "クレパスキュラー",
          "勝率(%)": 17.3,
          "スコア": -0.116,
          "calibrated_prob(%)": 6.44,
          "単勝": 2.0,
          "人気": 1,
          "期待値": 0.13
        },
        {
          "予測順位": 2,
          "馬番": 8,
          "馬名": "マイネルシンベリン",
          "勝率(%)": 11.0,
          "スコア": -0.571,
          "calibrated_prob(%)": 5.82,
          "単勝": 57.1,
          "人気": 13,
          "期待値": 3.32
        },
        {
          "予測順位": 3,
          "馬番": 16,
          "馬名": "サウンドムーブ",
          "勝率(%)": 9.7,
          "スコア": -0.701,
          "calibrated_prob(%)": 7.11,
          "単勝": 13.1,
          "人気": 5,
          "期待値": 0.93
        },
        {
          "予測順位": 4,
          "馬番": 15,
          "馬名": "アウダーシア",
          "勝率(%)": 8.6,
          "スコア": -0.817,
          "calibrated_prob(%)": 5.33,
          "単勝": 16.5,
          "人気": 7,
          "期待値": 0.88
        },
        {
          "予測順位": 5,
          "馬番": 14,
          "馬名": "アクロフェイズ",
          "勝率(%)": 8.0,
          "スコア": -0.89,
          "calibrated_prob(%)": 3.84,
          "単勝": 25.6,
          "人気": 10,
          "期待値": 0.98
        },
        {
          "予測順位": 6,
          "馬番": 1,
          "馬名": "ロードレイジング",
          "勝率(%)": 6.5,
          "スコア": -1.095,
          "calibrated_prob(%)": 3.49,
          "単勝": 204.0,
          "人気": 15,
          "期待値": 7.12
        },
        {
          "予測順位": 7,
          "馬番": 13,
          "馬名": "ミスターライト",
          "勝率(%)": 5.5,
          "スコア": -1.267,
          "calibrated_prob(%)": 2.63,
          "単勝": 12.9,
          "人気": 3,
          "期待値": 0.34
        },
        {
          "予測順位": 8,
          "馬番": 9,
          "馬名": "マカナアネラ",
          "勝率(%)": 4.9,
          "スコア": -1.382,
          "calibrated_prob(%)": 2.68,
          "単勝": 206.5,
          "人気": 16,
          "期待値": 5.53
        },
        {
          "予測順位": 9,
          "馬番": 7,
          "馬名": "ジーネキング",
          "勝率(%)": 4.3,
          "スコア": -1.505,
          "calibrated_prob(%)": 3.37,
          "単勝": 51.3,
          "人気": 11,
          "期待値": 1.73
        },
        {
          "予測順位": 10,
          "馬番": 2,
          "馬名": "アスクエジンバラ",
          "勝率(%)": 4.3,
          "スコア": -1.518,
          "calibrated_prob(%)": 3.09,
          "単勝": 5.2,
          "人気": 2,
          "期待値": 0.16
        },
        {
          "予測順位": 11,
          "馬番": 3,
          "馬名": "タイキルッジェーロ",
          "勝率(%)": 4.1,
          "スコア": -1.558,
          "calibrated_prob(%)": 2.55,
          "単勝": 55.2,
          "人気": 12,
          "期待値": 1.41
        },
        {
          "予測順位": 12,
          "馬番": 11,
          "馬名": "テルヒコウ",
          "勝率(%)": 3.9,
          "スコア": -1.602,
          "calibrated_prob(%)": 3.17,
          "単勝": 18.4,
          "人気": 8,
          "期待値": 0.58
        },
        {
          "予測順位": 13,
          "馬番": 4,
          "馬名": "ラストスマイル",
          "勝率(%)": 3.7,
          "スコア": -1.648,
          "calibrated_prob(%)": 1.95,
          "単勝": 14.4,
          "人気": 6,
          "期待値": 0.28
        },
        {
          "予測順位": 14,
          "馬番": 10,
          "馬名": "サノノグレーター",
          "勝率(%)": 2.8,
          "スコア": -1.924,
          "calibrated_prob(%)": 2.12,
          "単勝": 13.0,
          "人気": 4,
          "期待値": 0.28
        },
        {
          "予測順位": 15,
          "馬番": 6,
          "馬名": "ガリレア",
          "勝率(%)": 2.7,
          "スコア": -1.978,
          "calibrated_prob(%)": 2.63,
          "単勝": 20.9,
          "人気": 9,
          "期待値": 0.55
        },
        {
          "予測順位": 16,
          "馬番": 5,
          "馬名": "フレイムスター",
          "勝率(%)": 2.6,
          "スコア": -2.021,
          "calibrated_prob(%)": 2.26,
          "単勝": 172.1,
          "人気": 14,
          "期待値": 3.89
        }
      ],
      "odds_status": "middle",
      "recommendation": {
        "パターン": "混戦型",
        "パターン説明": "上位2〜3頭が拮抗 → 馬連・ワイド中心",
        "推奨買い目": [
          {
            "馬券種": "馬連",
            "買い目": "12-8",
            "理由": "上位2頭が拮抗（クレパスキュラー17.3% / マイネルシンベリン11.0%）"
          },
          {
            "馬券種": "ワイド",
            "買い目": "12-8",
            "理由": "クレパスキュラーとマイネルシンベリンの組み合わせ"
          },
          {
            "馬券種": "ワイド",
            "買い目": "12-16",
            "理由": "クレパスキュラーとサウンドムーブの組み合わせ"
          },
          {
            "馬券種": "ワイド",
            "買い目": "8-16",
            "理由": "マイネルシンベリンとサウンドムーブの組み合わせ"
          },
          {
            "馬券種": "単勝",
            "買い目": "8 マイネルシンベリン",
            "理由": "EV 3.32 > 1.0（勝率11.0% × オッズ57.1倍）"
          },
          {
            "馬券種": "単勝",
            "買い目": "1 ロードレイジング",
            "理由": "EV 7.12 > 1.0（勝率6.5% × オッズ204.0倍）"
          },
          {
            "馬券種": "単勝",
            "買い目": "9 マカナアネラ",
            "理由": "EV 5.53 > 1.0（勝率4.9% × オッズ206.5倍）"
          },
          {
            "馬券種": "単勝",
            "買い目": "7 ジーネキング",
            "理由": "EV 1.73 > 1.0（勝率4.3% × オッズ51.3倍）"
          },
          {
            "馬券種": "単勝",
            "買い目": "3 タイキルッジェーロ",
            "理由": "EV 1.41 > 1.0（勝率4.1% × オッズ55.2倍）"
          },
          {
            "馬券種": "単勝",
            "買い目": "5 フレイムスター",
            "理由": "EV 3.89 > 1.0（勝率2.6% × オッズ172.1倍）"
          }
        ],
        "勝負度": 1,
        "勝負度ラベル": "★",
        "勝負度理由": "モデル1位=1番人気（的中率高・配当低め）／混戦型／オッズ2.0倍（低オッズ）",
        "勝負度推奨": false,
        "妙味診断": "低",
        "妙味理由": "モデル1位=1番人気（的中率高・配当低め）／混戦型／オッズ2.0倍（低オッズ）",
        "期待値一覧": [
          {
            "馬番": 12,
            "馬名": "クレパスキュラー",
            "勝率(%)": 17.3,
            "calibrated_prob(%)": 6.44,
            "単勝": 2.0,
            "期待値": 0.13,
            "予測順位": 1
          },
          {
            "馬番": 8,
            "馬名": "マイネルシンベリン",
            "勝率(%)": 11.0,
            "calibrated_prob(%)": 5.82,
            "単勝": 57.1,
            "期待値": 3.32,
            "予測順位": 2
          },
          {
            "馬番": 16,
            "馬名": "サウンドムーブ",
            "勝率(%)": 9.7,
            "calibrated_prob(%)": 7.11,
            "単勝": 13.1,
            "期待値": 0.93,
            "予測順位": 3
          },
          {
            "馬番": 15,
            "馬名": "アウダーシア",
            "勝率(%)": 8.6,
            "calibrated_prob(%)": 5.33,
            "単勝": 16.5,
            "期待値": 0.88,
            "予測順位": 4
          },
          {
            "馬番": 14,
            "馬名": "アクロフェイズ",
            "勝率(%)": 8.0,
            "calibrated_prob(%)": 3.84,
            "単勝": 25.6,
            "期待値": 0.98,
            "予測順位": 5
          },
          {
            "馬番": 1,
            "馬名": "ロードレイジング",
            "勝率(%)": 6.5,
            "calibrated_prob(%)": 3.49,
            "単勝": 204.0,
            "期待値": 7.12,
            "予測順位": 6
          },
          {
            "馬番": 13,
            "馬名": "ミスターライト",
            "勝率(%)": 5.5,
            "calibrated_prob(%)": 2.63,
            "単勝": 12.9,
            "期待値": 0.34,
            "予測順位": 7
          },
          {
            "馬番": 9,
            "馬名": "マカナアネラ",
            "勝率(%)": 4.9,
            "calibrated_prob(%)": 2.68,
            "単勝": 206.5,
            "期待値": 5.53,
            "予測順位": 8
          },
          {
            "馬番": 7,
            "馬名": "ジーネキング",
            "勝率(%)": 4.3,
            "calibrated_prob(%)": 3.37,
            "単勝": 51.3,
            "期待値": 1.73,
            "予測順位": 9
          },
          {
            "馬番": 2,
            "馬名": "アスクエジンバラ",
            "勝率(%)": 4.3,
            "calibrated_prob(%)": 3.09,
            "単勝": 5.2,
            "期待値": 0.16,
            "予測順位": 10
          },
          {
            "馬番": 3,
            "馬名": "タイキルッジェーロ",
            "勝率(%)": 4.1,
            "calibrated_prob(%)": 2.55,
            "単勝": 55.2,
            "期待値": 1.41,
            "予測順位": 11
          },
          {
            "馬番": 11,
            "馬名": "テルヒコウ",
            "勝率(%)": 3.9,
            "calibrated_prob(%)": 3.17,
            "単勝": 18.4,
            "期待値": 0.58,
            "予測順位": 12
          },
          {
            "馬番": 4,
            "馬名": "ラストスマイル",
            "勝率(%)": 3.7,
            "calibrated_prob(%)": 1.95,
            "単勝": 14.4,
            "期待値": 0.28,
            "予測順位": 13
          },
          {
            "馬番": 10,
            "馬名": "サノノグレーター",
            "勝率(%)": 2.8,
            "calibrated_prob(%)": 2.12,
            "単勝": 13.0,
            "期待値": 0.28,
            "予測順位": 14
          },
          {
            "馬番": 6,
            "馬名": "ガリレア",
            "勝率(%)": 2.7,
            "calibrated_prob(%)": 2.63,
            "単勝": 20.9,
            "期待値": 0.55,
            "予測順位": 15
          },
          {
            "馬番": 5,
            "馬名": "フレイムスター",
            "勝率(%)": 2.6,
            "calibrated_prob(%)": 2.26,
            "単勝": 172.1,
            "期待値": 3.89,
            "予測順位": 16
          }
        ]
      },
      "confidence": {
        "level": 1,
        "label": "★",
        "reason": "モデル1位=1番人気（的中率高・配当低め）／混戦型／オッズ2.0倍（低オッズ）",
        "recommended": false
      },
      "result": [
        {
          "着順": 1,
          "馬番": 15,
          "馬名": "アウダーシア",
          "タイム": "1:46.0",
          "単勝": 19.4,
          "人気": 8
        },
        {
          "着順": 2,
          "馬番": 2,
          "馬名": "アスクエジンバラ",
          "タイム": "1:46.0",
          "単勝": 4.9,
          "人気": 2
        },
        {
          "着順": 3,
          "馬番": 14,
          "馬名": "アクロフェイズ",
          "タイム": "1:46.0",
          "単勝": 17.0,
          "人気": 7
        },
        {
          "着順": 4,
          "馬番": 16,
          "馬名": "サウンドムーブ",
          "タイム": "1:46.2",
          "単勝": 15.0,
          "人気": 6
        },
        {
          "着順": 5,
          "馬番": 10,
          "馬名": "サノノグレーター",
          "タイム": "1:46.2",
          "単勝": 11.2,
          "人気": 4
        },
        {
          "着順": 6,
          "馬番": 4,
          "馬名": "ラストスマイル",
          "タイム": "1:46.3",
          "単勝": 14.2,
          "人気": 5
        },
        {
          "着順": 7,
          "馬番": 12,
          "馬名": "クレパスキュラー",
          "タイム": "1:46.4",
          "単勝": 2.0,
          "人気": 1
        },
        {
          "着順": 8,
          "馬番": 8,
          "馬名": "マイネルシンベリン",
          "タイム": "1:46.6",
          "単勝": 85.3,
          "人気": 13
        },
        {
          "着順": 9,
          "馬番": 13,
          "馬名": "ミスターライト",
          "タイム": "1:46.6",
          "単勝": 7.9,
          "人気": 3
        },
        {
          "着順": 10,
          "馬番": 6,
          "馬名": "ガリレア",
          "タイム": "1:46.7",
          "単勝": 55.6,
          "人気": 10
        },
        {
          "着順": 11,
          "馬番": 3,
          "馬名": "タイキルッジェーロ",
          "タイム": "1:46.8",
          "単勝": 71.0,
          "人気": 11
        },
        {
          "着順": 12,
          "馬番": 7,
          "馬名": "ジーネキング",
          "タイム": "1:46.9",
          "単勝": 73.5,
          "人気": 12
        },
        {
          "着順": 13,
          "馬番": 9,
          "馬名": "マカナアネラ",
          "タイム": "1:47.6",
          "単勝": 385.8,
          "人気": 15
        },
        {
          "着順": 14,
          "馬番": 11,
          "馬名": "テルヒコウ",
          "タイム": "1:48.1",
          "単勝": 24.4,
          "人気": 9
        },
        {
          "着順": 15,
          "馬番": 1,
          "馬名": "ロードレイジング",
          "タイム": "1:48.4",
          "単勝": 426.0,
          "人気": 16
        },
        {
          "着順": 16,
          "馬番": 5,
          "馬名": "フレイムスター",
          "タイム": "1:49.0",
          "単勝": 312.1,
          "人気": 14
        }
      ]
    },
    {
      "race_id": "202607010211",
      "race_name": "金鯱賞",
      "grade": "G2",
      "venue": "中京",
      "distance": "芝2000m",
      "track_condition": "",
      "predicted_at": "2026-03-15T13:30:09",
      "predictions": [
        {
          "予測順位": 1,
          "馬番": 1,
          "馬名": "ドゥラドーレス",
          "勝率(%)": 19.3,
          "スコア": 0.24,
          "calibrated_prob(%)": 11.11,
          "単勝": 6.4,
          "人気": 2,
          "期待値": 0.71
        },
        {
          "予測順位": 2,
          "馬番": 6,
          "馬名": "ヴィレム",
          "勝率(%)": 14.7,
          "スコア": -0.03,
          "calibrated_prob(%)": 6.43,
          "単勝": 6.6,
          "人気": 3,
          "期待値": 0.42
        },
        {
          "予測順位": 3,
          "馬番": 3,
          "馬名": "ジョバンニ",
          "勝率(%)": 10.0,
          "スコア": -0.417,
          "calibrated_prob(%)": 4.72,
          "単勝": 8.6,
          "人気": 5,
          "期待値": 0.41
        },
        {
          "予測順位": 4,
          "馬番": 2,
          "馬名": "ジューンテイク",
          "勝率(%)": 9.6,
          "スコア": -0.456,
          "calibrated_prob(%)": 1.79,
          "単勝": 8.2,
          "人気": 4,
          "期待値": 0.15
        },
        {
          "予測順位": 5,
          "馬番": 9,
          "馬名": "シェイクユアハート",
          "勝率(%)": 9.4,
          "スコア": -0.477,
          "calibrated_prob(%)": 4.07,
          "単勝": 11.2,
          "人気": 8,
          "期待値": 0.46
        },
        {
          "予測順位": 6,
          "馬番": 5,
          "馬名": "ディマイザキッド",
          "勝率(%)": 7.7,
          "スコア": -0.683,
          "calibrated_prob(%)": 3.84,
          "単勝": 30.2,
          "人気": 10,
          "期待値": 1.16
        },
        {
          "予測順位": 7,
          "馬番": 4,
          "馬名": "アーバンシック",
          "勝率(%)": 6.4,
          "スコア": -0.863,
          "calibrated_prob(%)": 2.2,
          "単勝": 10.4,
          "人気": 7,
          "期待値": 0.23
        },
        {
          "予測順位": 8,
          "馬番": 14,
          "馬名": "サフィラ",
          "勝率(%)": 4.9,
          "スコア": -1.12,
          "calibrated_prob(%)": 3.77,
          "単勝": 64.9,
          "人気": 12,
          "期待値": 2.45
        },
        {
          "予測順位": 9,
          "馬番": 12,
          "馬名": "クイーンズウォーク",
          "勝率(%)": 4.6,
          "スコア": -1.203,
          "calibrated_prob(%)": 2.82,
          "単勝": 3.5,
          "人気": 1,
          "期待値": 0.1
        },
        {
          "予測順位": 10,
          "馬番": 10,
          "馬名": "セキトバイースト",
          "勝率(%)": 4.0,
          "スコア": -1.343,
          "calibrated_prob(%)": 2.64,
          "単勝": 20.1,
          "人気": 9,
          "期待値": 0.53
        },
        {
          "予測順位": 11,
          "馬番": 7,
          "馬名": "ニシノレヴナント",
          "勝率(%)": 3.5,
          "スコア": -1.462,
          "calibrated_prob(%)": 2.24,
          "単勝": 66.0,
          "人気": 13,
          "期待値": 1.48
        },
        {
          "予測順位": 12,
          "馬番": 11,
          "馬名": "キングズパレス",
          "勝率(%)": 2.9,
          "スコア": -1.645,
          "calibrated_prob(%)": 3.13,
          "単勝": 52.7,
          "人気": 11,
          "期待値": 1.65
        },
        {
          "予測順位": 13,
          "馬番": 13,
          "馬名": "ホウオウビスケッツ",
          "勝率(%)": 1.8,
          "スコア": -2.154,
          "calibrated_prob(%)": 2.12,
          "単勝": 10.3,
          "人気": 6,
          "期待値": 0.22
        },
        {
          "予測順位": 14,
          "馬番": 8,
          "馬名": "アラタ",
          "勝率(%)": 1.2,
          "スコア": -2.501,
          "calibrated_prob(%)": 0.88,
          "単勝": 88.4,
          "人気": 14,
          "期待値": 0.78
        }
      ],
      "odds_status": "middle",
      "recommendation": {
        "パターン": "混戦型",
        "パターン説明": "上位2〜3頭が拮抗 → 馬連・ワイド中心",
        "推奨買い目": [
          {
            "馬券種": "馬連",
            "買い目": "1-6",
            "理由": "上位2頭が拮抗（ドゥラドーレス19.3% / ヴィレム14.7%）"
          },
          {
            "馬券種": "ワイド",
            "買い目": "1-6",
            "理由": "ドゥラドーレスとヴィレムの組み合わせ"
          },
          {
            "馬券種": "ワイド",
            "買い目": "1-3",
            "理由": "ドゥラドーレスとジョバンニの組み合わせ"
          },
          {
            "馬券種": "ワイド",
            "買い目": "6-3",
            "理由": "ヴィレムとジョバンニの組み合わせ"
          },
          {
            "馬券種": "単勝",
            "買い目": "5 ディマイザキッド",
            "理由": "EV 1.16 > 1.0（勝率7.7% × オッズ30.2倍）"
          },
          {
            "馬券種": "単勝",
            "買い目": "14 サフィラ",
            "理由": "EV 2.45 > 1.0（勝率4.9% × オッズ64.9倍）"
          },
          {
            "馬券種": "単勝",
            "買い目": "7 ニシノレヴナント",
            "理由": "EV 1.48 > 1.0（勝率3.5% × オッズ66.0倍）"
          },
          {
            "馬券種": "単勝",
            "買い目": "11 キングズパレス",
            "理由": "EV 1.65 > 1.0（勝率2.9% × オッズ52.7倍）"
          }
        ],
        "勝負度": 3,
        "勝負度ラベル": "★★★",
        "勝負度理由": "モデル1位が2番人気（回収率89.4%帯）／混戦型／勝率差4.6%／オッズ6.4倍（3〜10倍帯: 回収率87.2%）",
        "勝負度推奨": true,
        "妙味診断": "高",
        "妙味理由": "モデル1位が2番人気（回収率89.4%帯）／混戦型／勝率差4.6%／オッズ6.4倍（3〜10倍帯: 回収率87.2%）",
        "期待値一覧": [
          {
            "馬番": 1,
            "馬名": "ドゥラドーレス",
            "勝率(%)": 19.3,
            "calibrated_prob(%)": 11.11,
            "単勝": 6.4,
            "期待値": 0.71,
            "予測順位": 1
          },
          {
            "馬番": 6,
            "馬名": "ヴィレム",
            "勝率(%)": 14.7,
            "calibrated_prob(%)": 6.43,
            "単勝": 6.6,
            "期待値": 0.42,
            "予測順位": 2
          },
          {
            "馬番": 3,
            "馬名": "ジョバンニ",
            "勝率(%)": 10.0,
            "calibrated_prob(%)": 4.72,
            "単勝": 8.6,
            "期待値": 0.41,
            "予測順位": 3
          },
          {
            "馬番": 2,
            "馬名": "ジューンテイク",
            "勝率(%)": 9.6,
            "calibrated_prob(%)": 1.79,
            "単勝": 8.2,
            "期待値": 0.15,
            "予測順位": 4
          },
          {
            "馬番": 9,
            "馬名": "シェイクユアハート",
            "勝率(%)": 9.4,
            "calibrated_prob(%)": 4.07,
            "単勝": 11.2,
            "期待値": 0.46,
            "予測順位": 5
          },
          {
            "馬番": 5,
            "馬名": "ディマイザキッド",
            "勝率(%)": 7.7,
            "calibrated_prob(%)": 3.84,
            "単勝": 30.2,
            "期待値": 1.16,
            "予測順位": 6
          },
          {
            "馬番": 4,
            "馬名": "アーバンシック",
            "勝率(%)": 6.4,
            "calibrated_prob(%)": 2.2,
            "単勝": 10.4,
            "期待値": 0.23,
            "予測順位": 7
          },
          {
            "馬番": 14,
            "馬名": "サフィラ",
            "勝率(%)": 4.9,
            "calibrated_prob(%)": 3.77,
            "単勝": 64.9,
            "期待値": 2.45,
            "予測順位": 8
          },
          {
            "馬番": 12,
            "馬名": "クイーンズウォーク",
            "勝率(%)": 4.6,
            "calibrated_prob(%)": 2.82,
            "単勝": 3.5,
            "期待値": 0.1,
            "予測順位": 9
          },
          {
            "馬番": 10,
            "馬名": "セキトバイースト",
            "勝率(%)": 4.0,
            "calibrated_prob(%)": 2.64,
            "単勝": 20.1,
            "期待値": 0.53,
            "予測順位": 10
          },
          {
            "馬番": 7,
            "馬名": "ニシノレヴナント",
            "勝率(%)": 3.5,
            "calibrated_prob(%)": 2.24,
            "単勝": 66.0,
            "期待値": 1.48,
            "予測順位": 11
          },
          {
            "馬番": 11,
            "馬名": "キングズパレス",
            "勝率(%)": 2.9,
            "calibrated_prob(%)": 3.13,
            "単勝": 52.7,
            "期待値": 1.65,
            "予測順位": 12
          },
          {
            "馬番": 13,
            "馬名": "ホウオウビスケッツ",
            "勝率(%)": 1.8,
            "calibrated_prob(%)": 2.12,
            "単勝": 10.3,
            "期待値": 0.22,
            "予測順位": 13
          },
          {
            "馬番": 8,
            "馬名": "アラタ",
            "勝率(%)": 1.2,
            "calibrated_prob(%)": 0.88,
            "単勝": 88.4,
            "期待値": 0.78,
            "予測順位": 14
          }
        ]
      },
      "confidence": {
        "level": 3,
        "label": "★★★",
        "reason": "モデル1位が2番人気（回収率89.4%帯）／混戦型／勝率差4.6%／オッズ6.4倍（3〜10倍帯: 回収率87.2%）",
        "recommended": true
      },
      "result": [
        {
          "着順": 1,
          "馬番": 9,
          "馬名": "シェイクユアハート",
          "タイム": "1:58.1",
          "単勝": 13.5,
          "人気": 8
        },
        {
          "着順": 2,
          "馬番": 3,
          "馬名": "ジョバンニ",
          "タイム": "1:58.1",
          "単勝": 8.7,
          "人気": 6
        },
        {
          "着順": 3,
          "馬番": 12,
          "馬名": "クイーンズウォーク",
          "タイム": "1:58.2",
          "単勝": 3.6,
          "人気": 1
        },
        {
          "着順": 4,
          "馬番": 2,
          "馬名": "ジューンテイク",
          "タイム": "1:58.2",
          "単勝": 7.7,
          "人気": 5
        },
        {
          "着順": 5,
          "馬番": 1,
          "馬名": "ドゥラドーレス",
          "タイム": "1:58.2",
          "単勝": 5.6,
          "人気": 2
        },
        {
          "着順": 6,
          "馬番": 6,
          "馬名": "ヴィレム",
          "タイム": "1:58.2",
          "単勝": 6.4,
          "人気": 3
        },
        {
          "着順": 7,
          "馬番": 5,
          "馬名": "ディマイザキッド",
          "タイム": "1:58.4",
          "単勝": 35.0,
          "人気": 10
        },
        {
          "着順": 8,
          "馬番": 11,
          "馬名": "キングズパレス",
          "タイム": "1:58.6",
          "単勝": 73.5,
          "人気": 11
        },
        {
          "着順": 9,
          "馬番": 14,
          "馬名": "サフィラ",
          "タイム": "1:58.6",
          "単勝": 88.9,
          "人気": 12
        },
        {
          "着順": 10,
          "馬番": 8,
          "馬名": "アラタ",
          "タイム": "1:58.7",
          "単勝": 142.3,
          "人気": 14
        },
        {
          "着順": 11,
          "馬番": 10,
          "馬名": "セキトバイースト",
          "タイム": "1:59.0",
          "単勝": 24.8,
          "人気": 9
        },
        {
          "着順": 12,
          "馬番": 7,
          "馬名": "ニシノレヴナント",
          "タイム": "1:59.1",
          "単勝": 102.5,
          "人気": 13
        },
        {
          "着順": 12,
          "馬番": 13,
          "馬名": "ホウオウビスケッツ",
          "タイム": "1:59.1",
          "単勝": 7.3,
          "人気": 4
        },
        {
          "着順": 14,
          "馬番": 4,
          "馬名": "アーバンシック",
          "タイム": "1:59.1",
          "単勝": 11.9,
          "人気": 7
        }
      ]
    }
  ]
}