{
  "date": "2026-03-22",
  "generated_at": "2026-03-21T21:08:51",
  "mode": "evening",
  "races": [
    {
      "race_id": "202609011011",
      "race_name": "阪神大賞典",
      "grade": "G2",
      "venue": "阪神",
      "distance": "芝3000m",
      "track_condition": "",
      "predicted_at": "2026-03-21T21:04:34",
      "predictions": [
        {
          "予測順位": 1,
          "馬番": 6,
          "馬名": "レッドバンデ",
          "勝率(%)": 21.1,
          "スコア": 0.624,
          "calibrated_prob(%)": 5.99
        },
        {
          "予測順位": 2,
          "馬番": 5,
          "馬名": "ダノンシーマ",
          "勝率(%)": 20.2,
          "スコア": 0.583,
          "calibrated_prob(%)": 4.05
        },
        {
          "予測順位": 3,
          "馬番": 4,
          "馬名": "アクアヴァーナル",
          "勝率(%)": 13.8,
          "スコア": 0.2,
          "calibrated_prob(%)": 4.88
        },
        {
          "予測順位": 4,
          "馬番": 3,
          "馬名": "ファミリータイム",
          "勝率(%)": 12.2,
          "スコア": 0.076,
          "calibrated_prob(%)": 2.97
        },
        {
          "予測順位": 5,
          "馬番": 1,
          "馬名": "アドマイヤテラ",
          "勝率(%)": 9.5,
          "スコア": -0.175,
          "calibrated_prob(%)": 1.8
        },
        {
          "予測順位": 6,
          "馬番": 7,
          "馬名": "マイネルエンペラー",
          "勝率(%)": 6.9,
          "スコア": -0.496,
          "calibrated_prob(%)": 1.72
        },
        {
          "予測順位": 7,
          "馬番": 9,
          "馬名": "サンライズソレイユ",
          "勝率(%)": 6.1,
          "スコア": -0.618,
          "calibrated_prob(%)": 1.54
        },
        {
          "予測順位": 8,
          "馬番": 10,
          "馬名": "ダンディズム",
          "勝率(%)": 5.5,
          "スコア": -0.727,
          "calibrated_prob(%)": 1.33
        },
        {
          "予測順位": 9,
          "馬番": 2,
          "馬名": "シュヴァリエローズ",
          "勝率(%)": 2.8,
          "スコア": -1.409,
          "calibrated_prob(%)": 1.14
        },
        {
          "予測順位": 10,
          "馬番": 8,
          "馬名": "メイショウブレゲ",
          "勝率(%)": 2.0,
          "スコア": -1.744,
          "calibrated_prob(%)": 1.19
        }
      ]
    },
    {
      "race_id": "202607010411",
      "race_name": "愛知杯",
      "grade": "G3",
      "venue": "中京",
      "distance": "芝1400m",
      "track_condition": "",
      "predicted_at": "2026-03-21T21:08:51",
      "predictions": [
        {
          "予測順位": 1,
          "馬番": 7,
          "馬名": "チェルビアット",
          "勝率(%)": 9.9,
          "スコア": -0.725,
          "calibrated_prob(%)": 4.52
        },
        {
          "予測順位": 2,
          "馬番": 17,
          "馬名": "リラボニート",
          "勝率(%)": 8.5,
          "スコア": -0.878,
          "calibrated_prob(%)": 2.81
        },
        {
          "予測順位": 3,
          "馬番": 12,
          "馬名": "カルプスペルシュ",
          "勝率(%)": 8.5,
          "スコア": -0.878,
          "calibrated_prob(%)": 4.99
        },
        {
          "予測順位": 4,
          "馬番": 2,
          "馬名": "レディマリオン",
          "勝率(%)": 8.4,
          "スコア": -0.884,
          "calibrated_prob(%)": 2.08
        },
        {
          "予測順位": 5,
          "馬番": 5,
          "馬名": "ウイントワイライト",
          "勝率(%)": 7.5,
          "スコア": -1.008,
          "calibrated_prob(%)": 2.48
        },
        {
          "予測順位": 6,
          "馬番": 6,
          "馬名": "ナムラクララ",
          "勝率(%)": 6.6,
          "スコア": -1.136,
          "calibrated_prob(%)": 4.31
        },
        {
          "予測順位": 7,
          "馬番": 18,
          "馬名": "アイサンサン",
          "勝率(%)": 6.4,
          "スコア": -1.159,
          "calibrated_prob(%)": 2.11
        },
        {
          "予測順位": 8,
          "馬番": 8,
          "馬名": "ソルトクィーン",
          "勝率(%)": 6.3,
          "スコア": -1.168,
          "calibrated_prob(%)": 4.4
        },
        {
          "予測順位": 9,
          "馬番": 16,
          "馬名": "ドロップオブライト",
          "勝率(%)": 6.0,
          "スコア": -1.23,
          "calibrated_prob(%)": 2.77
        },
        {
          "予測順位": 10,
          "馬番": 1,
          "馬名": "マピュース",
          "勝率(%)": 4.7,
          "スコア": -1.473,
          "calibrated_prob(%)": 1.87
        },
        {
          "予測順位": 11,
          "馬番": 14,
          "馬名": "シンバーシア",
          "勝率(%)": 4.5,
          "スコア": -1.521,
          "calibrated_prob(%)": 2.47
        },
        {
          "予測順位": 12,
          "馬番": 10,
          "馬名": "セフィロ",
          "勝率(%)": 4.3,
          "スコア": -1.557,
          "calibrated_prob(%)": 2.4
        },
        {
          "予測順位": 13,
          "馬番": 13,
          "馬名": "アブキールベイ",
          "勝率(%)": 4.3,
          "スコア": -1.565,
          "calibrated_prob(%)": 1.59
        },
        {
          "予測順位": 14,
          "馬番": 4,
          "馬名": "カンパニョーラ",
          "勝率(%)": 3.7,
          "スコア": -1.698,
          "calibrated_prob(%)": 1.42
        },
        {
          "予測順位": 15,
          "馬番": 3,
          "馬名": "モリノドリーム",
          "勝率(%)": 3.0,
          "スコア": -1.918,
          "calibrated_prob(%)": 1.74
        },
        {
          "予測順位": 16,
          "馬番": 11,
          "馬名": "スリールミニョン",
          "勝率(%)": 2.8,
          "スコア": -1.976,
          "calibrated_prob(%)": 0.8
        },
        {
          "予測順位": 17,
          "馬番": 15,
          "馬名": "ワイドラトゥール",
          "勝率(%)": 2.7,
          "スコア": -2.017,
          "calibrated_prob(%)": 0.72
        },
        {
          "予測順位": 18,
          "馬番": 9,
          "馬名": "マサノカナリア",
          "勝率(%)": 2.0,
          "スコア": -2.34,
          "calibrated_prob(%)": 1.22
        }
      ]
    }
  ]
}